Workbook

Sheet 假设开发法
A1: 假设开发法测算
A2: 估价对象: [请输入地址] | C2: 价值时点: [日期] | D2: 方法: 动态分析法
A3: 图例: 蓝字=可修改输入 | 黑字=公式 | 黄底=关键参数 | 红字=红线检查
A5: 一、最佳开发经营方式
A6: 开发完成后用途 | C6: 规模 (m²)
A7: 经营方式
A9: 二、开发经营期 (月)
A10: 前期 | C10: 建造期
A11: 销售期 | C11: 开发经营期总计 | D11: =ROUND(B10+C10,0)
A13: 三、开发完成后价值 (⚠️ 4.5.7条第1款: 不得用成本法)
A14: 测算方法 | C14: 数据来源
A15: 单价 (元/m²) | B15: 25000 | C15: 总价 (元) | D15: =ROUND(B15*B7,0)
A16: 信源等级 | C16: 建筑面积 (m²) | D16: =B7
A18: 四、后续开发必要支出
A19: 项目 | B19: 金额 (元) | C19: 参数 | D19: 发生期 (月)
A20: 建设成本
A21: 管理费用 | B21: =ROUND(B17*管理费率,0) | C21: 见参数表
A22: 销售费用 | B22: =ROUND(D14*销售费率,0) | C22: 见参数表
A23: 销售税费 | B23: =ROUND(D15*税率,0) | C23: 见参数表
A24: 取得税费 (仅转让前提)
A25: 支出合计 | B25: =ROUND(SUM(B20:B24),0)
A27: 五、折现率/利息/利润
A28: 折现率 r (动态法) | C28: 利率 (静态法)
A29: 利润率 (静态法)
A31: 六、开发价值 (动态法)
A32: 开发完成后价值折现 (元) | B32: =ROUND(D16/(1+B28)^((C11+C10)/12),0) | C32: 折现期=建造期+销售期, 转年
A33: 建设成本折现 (元) | B33: =ROUND(B20/(1+B28)^(D20/12),0) | C33: 按发生期分别折现
A34: 管理费用折现 (元) | B34: =ROUND(B21/(1+B28)^(D21/12),0)
A35: 销售费用折现 (元) | B35: =ROUND(B22/(1+B28)^(D22/12),0)
A36: 销售税费折现 (元) | B36: =ROUND(B23/(1+B28)^(D23/12),0)
A37: 取得税费折现 (元)(如有) | B37: =ROUND(B24/(1+B28)^(D24/12),0) | C37: 仅转让开发前提
A38: 支出折现合计 (元) | B38: =ROUND(SUM(B33:B37),0)
A39: 开发价值 总价 (元) | B39: =ROUND(B32-B38,0)
A40: 建筑面积 (m²) | B40: =B7
A41: 开发价值 单价 (元/m²) | B41: =ROUND(B39/B40,0)
A43: 七、红线检查
A44: 开发完成后价值方法 | B44: =IF(B15="成本法","✗ 违规: 4.5.7条禁止用成本法","✓ 合规: 比较法/收益法")
A45: 利息/利润重复检查 | B45: =IF(D2<>"静态","✓ 动态法无需另算利息利润","⚠ 静态法: 确认未重复计算")
A46: 估价前提匹配检查 | B46: =IF(AND(D2="被迫转让开发", B28<0.08),"⚠ 抵押估价折现率宜≥8%","✓")

Sheet 现金流时间线
A1: 现金流时间线 (动态分析法)
A3: 期数(月) | B3: 现金流入 (元) | C3: 现金流出 (元) | D3: 净现金流 (元) | E3: 折现因子
A4: 0 | B4: 0 | D4: =ROUND(B4-C4,0) | E4: =1/(1+假设开发法!B27)^(A4/12)
A5: 1 | D5: =ROUND(B5-C5,0) | E5: =1/(1+假设开发法!B27)^(A5/12)
A6: 2 | D6: =ROUND(B6-C6,0) | E6: =1/(1+假设开发法!B27)^(A6/12)
A7: 3 | D7: =ROUND(B7-C7,0) | E7: =1/(1+假设开发法!B27)^(A7/12)
A8: 4 | D8: =ROUND(B8-C8,0) | E8: =1/(1+假设开发法!B27)^(A8/12)
A9: 5 | D9: =ROUND(B9-C9,0) | E9: =1/(1+假设开发法!B27)^(A9/12)
A10: 6 | D10: =ROUND(B10-C10,0) | E10: =1/(1+假设开发法!B27)^(A10/12)
A11: 7 | D11: =ROUND(B11-C11,0) | E11: =1/(1+假设开发法!B27)^(A11/12)
A12: 8 | D12: =ROUND(B12-C12,0) | E12: =1/(1+假设开发法!B27)^(A12/12)
A13: 9 | D13: =ROUND(B13-C13,0) | E13: =1/(1+假设开发法!B27)^(A13/12)
A14: 10 | D14: =ROUND(B14-C14,0) | E14: =1/(1+假设开发法!B27)^(A14/12)
A15: 11 | D15: =ROUND(B15-C15,0) | E15: =1/(1+假设开发法!B27)^(A15/12)
A16: 12 | D16: =ROUND(B16-C16,0) | E16: =1/(1+假设开发法!B27)^(A16/12)
A17: 13 | D17: =ROUND(B17-C17,0) | E17: =1/(1+假设开发法!B27)^(A17/12)
A18: 14 | D18: =ROUND(B18-C18,0) | E18: =1/(1+假设开发法!B27)^(A18/12)
A19: 15 | D19: =ROUND(B19-C19,0) | E19: =1/(1+假设开发法!B27)^(A19/12)
A20: 16 | D20: =ROUND(B20-C20,0) | E20: =1/(1+假设开发法!B27)^(A20/12)
A21: 17 | D21: =ROUND(B21-C21,0) | E21: =1/(1+假设开发法!B27)^(A21/12)
A22: 18 | D22: =ROUND(B22-C22,0) | E22: =1/(1+假设开发法!B27)^(A22/12)
A23: 19 | D23: =ROUND(B23-C23,0) | E23: =1/(1+假设开发法!B27)^(A23/12)
A24: 20 | D24: =ROUND(B24-C24,0) | E24: =1/(1+假设开发法!B27)^(A24/12)
A25: 21 | D25: =ROUND(B25-C25,0) | E25: =1/(1+假设开发法!B27)^(A25/12)
A26: 22 | D26: =ROUND(B26-C26,0) | E26: =1/(1+假设开发法!B27)^(A26/12)
A27: 23 | D27: =ROUND(B27-C27,0) | E27: =1/(1+假设开发法!B27)^(A27/12)
A28: NPV (元) | D28: =ROUND(SUMPRODUCT(D4:D27,E4:E27),0)
